genepi/AppGenEpi.py
genepi/GenEpi.py
genepi/UCSCGenomeDatabase.txt
genepi/__init__.py
genepi/step0_correctMissingID.py
genepi/step1_downloadUCSCDB.py
genepi/step2_estimateLD.py
genepi/step3_splitByGene.py
genepi/step4_singleGeneEpistasis_Lasso.py
genepi/step4_singleGeneEpistasis_Logistic.py
genepi/step5_crossGeneEpistasis_Lasso.py
genepi/step5_crossGeneEpistasis_Logistic.py
genepi/step6_ensembleWithCovariates.py
genepi/step7_validateByIsolatedData.py
genepi/example/example.py
genepi/example/sample.csv
genepi/example/sample.gen
genepi/tools/__init__.py
genepi/tools/createGeneRef.py
genepi/tools/randomized_l1.py
genepi/tools/six.py
genepi/tools/vcf2oxford.py
genepi/tools/vcf2plot.py
genepi-2.0.10.dist-info/LICENSE
genepi-2.0.10.dist-info/METADATA
genepi-2.0.10.dist-info/WHEEL
genepi-2.0.10.dist-info/entry_points.txt
genepi-2.0.10.dist-info/top_level.txt
genepi-2.0.10.dist-info/RECORD
