Metadata-Version: 2.1
Name: genepi
Version: 2.0.10
Summary: A package for detecting epsitasis by machine learning
Home-page: https://github.com/Chester75321/GenEpi
Author: Chester (Yu-Chuan Chang)
Author-email: chester75321@gmail.com
License: MIT
Project-URL: Source Code, https://github.com/Chester75321/GenEpi
Project-URL: Documentation, https://genepi.readthedocs.io/en/latest/
Project-URL: Bug Tracker, https://github.com/Chester75321/GenEpi/issues
Keywords: epistasis,SNP-SNP interactions,GWAS
Platform: UNKNOWN
Classifier: Development Status :: 3 - Alpha
Classifier: Intended Audience :: Science/Research
Classifier: License :: OSI Approved :: MIT License
Classifier: Programming Language :: Python :: 3
Classifier: Programming Language :: Python :: 3.7
Classifier: Topic :: Scientific/Engineering :: Bio-Informatics
Classifier: Topic :: Scientific/Engineering :: Artificial Intelligence
Requires-Python: >=3.7
Requires-Dist: pymysql (>=0.8.0)
Requires-Dist: numpy (>=1.13.0)
Requires-Dist: scipy (>=0.19.0)
Requires-Dist: psutil (>=4.3.0)
Requires-Dist: scikit-learn (==0.21.2)
Requires-Dist: matplotlib (>=3.1.1)
Requires-Dist: pandas (>=0.25.2)
Requires-Dist: seaborn (>=0.9.0)
Requires-Dist: PyQt5 (==5.14.0)
